flimlib/__init__.py
flimlib/_flimlib.cp310-win32.pyd
flimlib/cfunc.py
flimlib-2.2.5.dist-info/licenses/LICENSE.txt
flimlib-2.2.5.dist-info/METADATA
flimlib-2.2.5.dist-info/WHEEL
flimlib-2.2.5.dist-info/top_level.txt
flimlib-2.2.5.dist-info/RECORD
