Metadata-Version: 2.4
Name: flimlib
Version: 2.2.5
Summary: A python wrapper for flimlib's C functions
Home-page: https://github.com/flimlib/flimlib
Author: Paul Barber, Curtis Rueden, Kevin Tan
Project-URL: Bug Tracker, https://github.com/flimlib/flimlib/issues
Classifier: Programming Language :: Python :: 3
Classifier: License :: OSI Approved :: GNU General Public License v3 (GPLv3)
Classifier: Operating System :: OS Independent
Requires-Python: >=3.8
License-File: LICENSE.txt
Requires-Dist: numpy>=1.12.0
Dynamic: license-file
Dynamic: requires-dist
